Radium/__init__.py
Radium/cli.py
Radium/RadiumBase/__init__.py
Radium/RadiumBase/application.py
Radium/RadiumBase/paths.py
Radium/RadiumBase/read.py
Radium/RadiumBase/run.py
Radium/RadiumBase/tempCodeRunnerFile.py
Radium/RadiumBase/Radium/__init__.py
Radium/RadiumBase/Radium/auth.py
Radium/RadiumBase/Radium/outputs.py
Radium/RadiumBase/Radium/request_class.py
Radium/RadiumBase/Radium/response.py
Radium/RadiumBase/Radium/tempCodeRunnerFile.py
Radium/RadiumBase/app/__init__.py
Radium/RadiumBase/app/@/__init__.py
Radium/RadiumBase/app/@/page.py
Radium/RadiumBase/auth/__init__.py
Radium/RadiumBase/auth/auth.py
Radium/RadiumBase/cli/__init__.py
Radium/RadiumBase/middlewares/__init__.py
Radium/RadiumBase/middlewares/middleware.py
Radium/RadiumBase/static/__init__.py
Radium/RadiumBase/supabase_utils/__init__.py
Radium/RadiumBase/supabase_utils/setup.py
Radium/RadiumBase/templates/__init__.py
radium_web-0.1.1.dist-info/METADATA
radium_web-0.1.1.dist-info/WHEEL
radium_web-0.1.1.dist-info/entry_points.txt
radium_web-0.1.1.dist-info/top_level.txt
radium_web-0.1.1.dist-info/RECORD
