Metadata-Version: 2.4
Name: radium-web
Version: 0.1.1
Summary: Radium – a WSGI based Python web framework
Author: Saksham Jain
License: MIT
Requires-Python: >=3.8
